EasyInject-0.3.dist-info/DESCRIPTION.rst
EasyInject-0.3.dist-info/METADATA
EasyInject-0.3.dist-info/RECORD
EasyInject-0.3.dist-info/WHEEL
EasyInject-0.3.dist-info/metadata.json
EasyInject-0.3.dist-info/top_level.txt
easyinject/__init__.py
easyinject/injector.py
